CHANGES.rst
CONTRIBUTORS.rst
MANIFEST.in
README.rst
bootstrap.py
buildout.cfg
setup.py
cpskin/__init__.py
cpskin.diazotheme.trendy.egg-info/PKG-INFO
cpskin.diazotheme.trendy.egg-info/SOURCES.txt
cpskin.diazotheme.trendy.egg-info/dependency_links.txt
cpskin.diazotheme.trendy.egg-info/entry_points.txt
cpskin.diazotheme.trendy.egg-info/namespace_packages.txt
cpskin.diazotheme.trendy.egg-info/not-zip-safe
cpskin.diazotheme.trendy.egg-info/requires.txt
cpskin.diazotheme.trendy.egg-info/top_level.txt
cpskin/diazotheme/__init__.py
cpskin/diazotheme/trendy/__init__.py
cpskin/diazotheme/trendy/configure.zcml
cpskin/diazotheme/trendy/upgradehandlers.py
cpskin/diazotheme/trendy/profiles/default/cssregistry.xml
cpskin/diazotheme/trendy/profiles/default/lessregistry.xml
cpskin/diazotheme/trendy/profiles/default/metadata.xml
cpskin/diazotheme/trendy/profiles/default/theme.xml
cpskin/diazotheme/trendy/profiles/uninstall/cssregistry.xml
cpskin/diazotheme/trendy/profiles/uninstall/lessregistry.xml
cpskin/diazotheme/trendy/static/manifest.cfg
cpskin/diazotheme/trendy/static/preview.png
cpskin/diazotheme/trendy/static/rules.xml
cpskin/diazotheme/trendy/static/css/theme-styles.css
cpskin/diazotheme/trendy/static/images/header.jpg
cpskin/diazotheme/trendy/static/less/styles.less
cpskin/diazotheme/trendy/static/less/variables.less
cpskin/diazotheme/trendy/static/rules/footer.xml
docs/LICENSE.GPL
docs/LICENSE.rst